ffmpeg_setpath/__init__.py
ffmpeg_setpath/examples.py
ffmpeg_setpath/ffmpeg_setpath.py
ffmpeg_setpath-1.0.0.dist-info/LICENSE
ffmpeg_setpath-1.0.0.dist-info/METADATA
ffmpeg_setpath-1.0.0.dist-info/WHEEL
ffmpeg_setpath-1.0.0.dist-info/top_level.txt
ffmpeg_setpath-1.0.0.dist-info/RECORD
