Metadata-Version: 2.2
Name: ffmpeg_setpath
Version: 1.0.0
Summary: ffmpeg_setpath is a Python library to automatically set the system paths of ffmpeg.
Author-email: Erdogan Taskesen <erdogant@gmail.com>
License: MIT License
Project-URL: Homepage, https://erdogant.github.io/ffmpeg_setpath
Project-URL: Download, https://github.com/erdogant/ffmpeg_setpath/archive/{version}.tar.gz
Keywords: Python,ffmpeg,system path
Classifier: Programming Language :: Python :: 3
Classifier: License :: OSI Approved :: MIT License
Classifier: Operating System :: OS Independent
Requires-Python: >=3
License-File: LICENSE
Requires-Dist: requests
